scapy_tui/__init__.py
scapy_tui/main.py
scapy_tui/scapy_tui_app.py
scapy_tui/screens/filter.py
scapy_tui/widgets/pkt_detail.py
scapy_tui/widgets/pkt_list.py
scapy_tui-0.0.3.dist-info/METADATA
scapy_tui-0.0.3.dist-info/WHEEL
scapy_tui-0.0.3.dist-info/entry_points.txt
scapy_tui-0.0.3.dist-info/licenses/LICENSE.md
scapy_tui-0.0.3.dist-info/RECORD
