Metadata-Version: 2.4
Name: scapy-tui
Version: 0.0.3
Summary: Analyze packets in an interactive text-based user interface.
Project-URL: Homepage, https://github.com/antoniovazquezblanco/scapy-tui
Project-URL: Bug Tracker, https://github.com/antoniovazquezblanco/scapy-tui/issues
Author-email: Antonio Vázquez Blanco <antoniovazquezblanco@gmail.com>
License: GPL-3.0-only
License-File: LICENSE.md
Keywords: scapy,tui,wireshark
Classifier: Intended Audience :: Developers
Classifier: Intended Audience :: Information Technology
Classifier: License :: OSI Approved :: GNU General Public License v3 (GPLv3)
Classifier: Operating System :: OS Independent
Classifier: Programming Language :: Python :: 3
Classifier: Topic :: Security
Requires-Python: >=3.0
Requires-Dist: scapy
Requires-Dist: textual
